faker_food/__init__.py
faker_food/categories.py
faker_food/dish_descriptions.py
faker_food/dishes.py
faker_food/ethnic_categories.py
faker_food/fruits.py
faker_food/ingredients.py
faker_food/measurements.py
faker_food/spices.py
faker_food/sushi.py
faker_food/vegetables.py
faker_food-0.3.0.dist-info/LICENSE
faker_food-0.3.0.dist-info/METADATA
faker_food-0.3.0.dist-info/WHEEL
faker_food-0.3.0.dist-info/RECORD
