Metadata-Version: 2.1
Name: faker_food
Version: 0.3.0
Summary: Food related provider for the Python Faker library
Home-page: https://github.com/madams74/faker_food
License: MIT
Keywords: faker,data,test,mock,generator,food
Author: Mark Adams
Author-email: madams74@gmail.com
Requires-Python: >=3.8
Classifier: Intended Audience :: Developers
Classifier: License :: OSI Approved :: MIT License
Classifier: Programming Language :: Python
Classifier: Programming Language :: Python :: 3
Classifier: Programming Language :: Python :: 3.8
Classifier: Programming Language :: Python :: 3.9
Classifier: Programming Language :: Python :: 3.10
Classifier: Programming Language :: Python :: 3.11
Classifier: Topic :: Software Development
Classifier: Topic :: Software Development :: Libraries :: Python Modules
Classifier: Topic :: Software Development :: Testing
Requires-Dist: Faker (>=12.0.0)
Project-URL: Repository, https://github.com/madams74/faker_food
